capnp/__init__.pxd
capnp/__init__.py
capnp/_gen.py
capnp/c++.capnp
capnp/persistent.capnp
capnp/rpc-twoparty.capnp
capnp/rpc.capnp
capnp/schema.capnp
capnp/stream.capnp
capnp/version.py
capnp/helpers/__init__.pxd
capnp/helpers/capabilityHelper.h
capnp/helpers/checkCompiler.h
capnp/helpers/deserialize.h
capnp/helpers/fixMaybe.h
capnp/helpers/helpers.pxd
capnp/helpers/non_circular.pxd
capnp/helpers/rpcHelper.h
capnp/helpers/serialize.h
capnp/includes/PyCustomMessageBuilder.h
capnp/includes/__init__.pxd
capnp/includes/capnp_cpp.pxd
capnp/includes/schema_cpp.pxd
capnp/includes/types.pxd
capnp/lib/__init__.pxd
capnp/lib/__init__.py
capnp/lib/capnp.cpython-310-aarch64-linux-gnu.so
capnp/lib/capnp.pxd
capnp/lib/capnp.pyx
capnp/lib/capnp_api.h
capnp/lib/pickle_helper.py
capnp/templates/module.pyx
capnp/templates/setup.py.tmpl
pycapnp.libs/libgcc_s-2d945d6c.so.1
pycapnp.libs/libstdc++-85f2cd6d.so.6.0.33
pycapnp-2.2.2.dist-info/METADATA
pycapnp-2.2.2.dist-info/WHEEL
pycapnp-2.2.2.dist-info/entry_points.txt
pycapnp-2.2.2.dist-info/top_level.txt
pycapnp-2.2.2.dist-info/RECORD
pycapnp-2.2.2.dist-info/licenses/LICENSE.md
