Metadata-Version: 2.4
Name: pycapnp
Version: 2.2.2
Summary: A cython wrapping of the C++ Cap'n Proto library
Home-page: https://github.com/capnproto/pycapnp
Download-URL: https://github.com/haata/pycapnp/archive/v2.2.2.zip
Author: Jacob Alexander
Author-email: haata@kiibohd.com
License: BSD-2-Clause
Keywords: capnp,capnproto,Cap'n Proto,pycapnp
Classifier: Development Status :: 5 - Production/Stable
Classifier: Intended Audience :: Developers
Classifier: Operating System :: MacOS :: MacOS X
Classifier: Operating System :: Microsoft :: Windows :: Windows 10
Classifier: Operating System :: POSIX
Classifier: Programming Language :: C++
Classifier: Programming Language :: Cython
Classifier: Programming Language :: Python :: 3.8
Classifier: Programming Language :: Python :: 3.9
Classifier: Programming Language :: Python :: 3.10
Classifier: Programming Language :: Python :: 3.11
Classifier: Programming Language :: Python :: 3.12
Classifier: Programming Language :: Python :: Implementation :: PyPy
Classifier: Topic :: Communications
Requires-Python: >=3.8
License-File: LICENSE.md
Dynamic: author
Dynamic: author-email
Dynamic: classifier
Dynamic: description
Dynamic: description-content-type
Dynamic: download-url
Dynamic: home-page
Dynamic: keywords
Dynamic: license
Dynamic: license-file
Dynamic: requires-python
Dynamic: summary
